ben_music_mcp/__init__.py
ben_music_mcp/action.py
ben_music_mcp/artists.json
ben_music_mcp/cookie.txt
ben_music_mcp/html_template.py
ben_music_mcp/styleList.json
ben_music_mcp/tool.py
ben_music_mcp/toplist.json
ben_music_mcp-0.1.20.dist-info/entry_points.txt
ben_music_mcp-0.1.20.dist-info/METADATA
ben_music_mcp-0.1.20.dist-info/WHEEL
ben_music_mcp-0.1.20.dist-info/RECORD
