Metadata-Version: 2.4
Name: ben-music-mcp
Version: 0.1.20
Summary: 本的乐mcp服务
Author: ben
Author-email: 2014911413@qq.com
Requires-Python: >=3.12
Classifier: Programming Language :: Python :: 3
Classifier: Programming Language :: Python :: 3.12
Classifier: Programming Language :: Python :: 3.13
Classifier: Programming Language :: Python :: 3.14
Requires-Dist: fastmcp (>=2.13.0.2)
Requires-Dist: psutil (>=6.1.1)
Requires-Dist: pyautogui (>=0.9.54)
Requires-Dist: requests (>=2.32.4)
Requires-Dist: uiautomation (>=2.0.20)
